topconjp2lib-1.1.data/purelib/topconjp2lib/__init__.py
topconjp2lib-1.1.data/purelib/topconjp2lib/topconopenjp2.dll
topconjp2lib-1.1.data/purelib/topconjp2lib/tpopenjp2.py
topconjp2lib-1.1.dist-info/METADATA
topconjp2lib-1.1.dist-info/WHEEL
topconjp2lib-1.1.dist-info/top_level.txt
topconjp2lib-1.1.dist-info/RECORD
