Metadata-Version: 2.1
Name: topconjp2lib
Version: 1.1
Summary: topcon openjp2 library
Home-page: UNKNOWN
License: UNKNOWN
Platform: UNKNOWN
Requires-Python: >=3.6
